Alu/Alu.v
module ALU(
A,
B,
Op,
R );

input[7:0] A,B;
input[2:0] Op;
output[7:0] R;
wire[7:0] Reg1,Reg2;
reg[7:0] Reg3;

assign Reg1 = A;
assign Reg2 = B;

assign R = Reg3;

always@(posedge Op or posedge Reg1 or posedge Reg2)

begin
case(Op)
0: Reg3 = Reg1 + Reg2; // Suma
1: Reg3 = Reg1 - Reg2;// resta
2: Reg3 =~Reg1;//NOT
3: Reg3 =~(Reg1 & Reg2);//NAND
4: Reg3 =~(Reg1 | Reg2);//NOR
5: Reg3 = Reg1 & Reg2;//AND
6: Reg3 = Reg1 | Reg2;//OR
7: Reg3 = Reg1 ^ Reg2;//XOR
endcase
end
endmodule

Alu/Alu_tb.v
module ALU_tb;
// Inputs
reg[7:0] A;
reg[7:0] B;
reg[2:0] Op;
// Outputs
wire[7:0] R;
// Instantiate the Unit Under Test (UUT)
ALU a1( A,B,Op,R);


initial begin
#10 $display(" ");
$display(" ");
$display(" Operaciones con ALU");
$display("A B Salida");
$display("____________");
$monitor(" %b    %b    %b   ", A ,B ,R);
end
// Apply inputs.
initial begin
A =8'b10101010;
B =8'b00001111;
Op =0;
#10 Op =1;
#10 Op =2;
#10 Op =3;
#10 Op =4;
#10 Op =5;
#10 Op =6;
#10 Op =7;
$finish;
end

initial begin
 $dumpfile("Alu_tb.vcd");
 $dumpvars(0,ALU_tb);
end

endmodule

Alu/Alu_tb.vcd
$date
	Sat Oct 24 17:24:37 2020
$end
$version
	Icarus Verilog
$end
$timescale
	1ps
$end
$scope module ALU_tb $end
$var wire 8 ! R [7:0] $end
$var reg 8 " A [7:0] $end
$var reg 8 # B [7:0] $end
$var reg 3 $ Op [2:0] $end
$scope module a1 $end
$var wire 8 % A [7:0] $end
$var wire 8 & B [7:0] $end
$var wire 3 ' Op [2:0] $end
$var wire 8 ( R [7:0] $end
$var wire 8 ) Reg1 [7:0] $end
$var wire 8 * Reg2 [7:0] $end
$var reg 8 + Reg3 [7:0] $end
$upscope $end
$upscope $end
$enddefinitions $end
#0
$dumpvars
b10111001 +
b1111 *
b10101010 )
b10111001 (
b0 '
b1111 &
b10101010 %
b0 $
b1111 #
b10101010 "
b10111001 !
$end
#10
b10011011 !
b10011011 (
b10011011 +
b1 $
b1 '
#20
b10 $
b10 '
#30
b11110101 !
b11110101 (
b11110101 +
b11 $
b11 '
#40
b100 $
b100 '
#50
b1010 !
b1010 (
b1010 +
b101 $
b101 '
#60
b110 $
b110 '
#70
b10100101 !
b10100101 (
b10100101 +
b111 $
b111 '
