Alu/Alu.v

// se declaran las variables
module ALU(
A,
B,
Op,
R );
// se declara el tipo
input[7:0] A,B;
input[2:0] Op;
output[7:0] R;
wire[7:0] Reg1,Reg2;
reg[7:0] Reg3;
// El reg1 y reg2 almacenan el valor de las entradas. El reg3 almacena el valor de la salida
assign Reg1 = A;
assign Reg2 = B;
assign R = Reg3;
// se declara que el codigo hará efecto cada vez que pasen por el valor no cero
always@(posedge Op or posedge Reg1 or posedge Reg2)

/*
Se declaran los diferentes casos con los que podremos evaluar nuestras entradas,
para luego en el testbench solamente escrbir por ejemplo op=1; y obtener la
operacion que se desea.
*/

begin
case(Op)
3'b010: Reg3 = Reg1 + Reg2; // Suma
3'b110: Reg3 = Reg1 - Reg2;// resta
//3'b100: Reg3 =~Reg1;//NOT
3'b100: Reg3 =(Reg1 & ~Reg2);// A and ~B
3'b101: Reg3 =(Reg1 | ~Reg2);// A or ~B
3'b000: Reg3 = Reg1 & Reg2;//AND
3'b001: Reg3 = Reg1 | Reg2;//OR
3'b111: if (Reg1 < Reg2) Reg3 =1;
        else Reg3 = 0;
endcase
end
endmodule

Alu/Alu_tb.v
module ALU_tb;
// Entradas
reg[7:0] A;
reg[7:0] B;
reg[2:0] Op;
// salidas
wire[7:0] R;
// instancia de nuestro codigo
ALU a1( A,B,Op,R);

// se inicia colocando un título a nuestras tablas y colocando los valores
// que deseamos que se desplieguen cuando se ejecute el testbench

initial begin
#10 $display(" ");
$display(" ");
$display(" Operaciones con ALU");
$display("A B Salida");
$display("____________");
$monitor(" %b    %b    %b   ", A ,B ,R);
end

initial begin
// Se colocan los valores que queremos operar
A =8'b10101010;
B =8'b00001111;

// se prueban las diferentes operaciones que se implementaron en el código.
Op =0;
#10 Op =1;
#10 Op =2;
#10 Op =3;
#10 Op =4;
#10 Op =5;
#10 Op =6;
#10 Op =7;
$finish;
end
// se crea archivos de gtkwave y para ver los diagramas de timing
initial begin
 $dumpfile("Alu_tb.vcd");
 $dumpvars(0,ALU_tb);
end

endmodule

Alu/Alu_tb.vcd
$date
	Sat Oct 24 20:21:25 2020
$end
$version
	Icarus Verilog
$end
$timescale
	1ps
$end
$scope module ALU_tb $end
$var wire 8 ! R [7:0] $end
$var reg 8 " A [7:0] $end
$var reg 8 # B [7:0] $end
$var reg 3 $ Op [2:0] $end
$scope module a1 $end
$var wire 8 % A [7:0] $end
$var wire 8 & B [7:0] $end
$var wire 3 ' Op [2:0] $end
$var wire 8 ( R [7:0] $end
$var wire 8 ) Reg1 [7:0] $end
$var wire 8 * Reg2 [7:0] $end
$var reg 8 + Reg3 [7:0] $end
$upscope $end
$upscope $end
$enddefinitions $end
#0
$dumpvars
b10111001 +
b1111 *
b10101010 )
b10111001 (
b0 '
b1111 &
b10101010 %
b0 $
b1111 #
b10101010 "
b10111001 !
$end
#10
b10011011 !
b10011011 (
b10011011 +
b1 $
b1 '
#20
b10 $
b10 '
#30
b11110101 !
b11110101 (
b11110101 +
b11 $
b11 '
#40
b100 $
b100 '
#50
b1010 !
b1010 (
b1010 +
b101 $
b101 '
#60
b110 $
b110 '
#70
b10100101 !
b10100101 (
b10100101 +
b111 $
b111 '
