Contador/lab8.v
module Contador (
clk,
enable,
rst,
load,
datos,
salidas
);

input clk;
input rst;
input enable;
input load;
input [11:0] datos;
output [11:0] salidas;

wire clk;
wire rst;
wire enable;
wire load;
wire [11:0] datos;

reg [11:0]   salidas;

always @(posedge clk or posedge rst)

begin: contadorr

if (rst)begin

salidas <= 000000000000;

end

else if (enable)begin

salidas<= salidas + 1;

end

else if (load)begin

salidas <= datos;

end
end //contadorr





endmodule

Contador/lab8_tb.v
module testbench();

reg clk, reset, enable, load;
reg [11:0] datos;
wire [11:0]  salidas;

Contador c1(clk, enable, reset, load, datos, salidas);

    initial begin
    #10 $display(" ");
    $display(" ");
    $display(" Contador de 12 bits");
    $display("clk enable load reset salidas");
    $display("_______________________________");
    $monitor(" %b    %b    %b   %b    %b  ", clk, enable, load, reset, salidas);
    end

  always// clock
  #5 clk = ~clk;
  initial begin
  // valor inicial
   datos =  12'b011011000110;//198

  #10 clk=0;
  #10 reset =0;
  #10 load =0;


  /*
  Caso en el que cargamos precargamos
  los datos y contamos a partir de ese dato ingresado
  */
  $display("Pre-cargar valor y contar a partir de ahí");

  datos =  12'b011011000110;//198
  #10  load = 1;
  #10 enable = 1;
  #10 enable = 1;
  #10 enable = 1;
  #10 enable = 1;
  #10 enable = 1;
  #10 enable = 1;
  #10 enable = 1;
  #10 enable = 1;
  #10 reset = 1;
  #10 reset=0;
  #10 load = 0;
   /// empezar a contar
   $display("Empezar a contar");
   #10 enable = 1;
   #10 enable = 1;
   #10 enable = 1;
   #10 enable = 1;
   #10 enable = 1;
   #10 enable = 1;
   #10 enable = 1;
   #10 enable = 1;
   #10 enable = 1;
   #10 enable = 1;
   #10 enable = 1;
   #10 enable = 1;
   #10 enable = 1;
   #10 enable = 1;
    #10 enable = 1;
     #10 enable = 1;
     #10 enable = 1;
     #10 enable = 1;
     #10 enable = 1;
     #10 enable = 1;
     #10 enable = 1;
     #10 enable = 1;
     #10 enable = 1;
     #10 enable = 1;
     #10 enable = 1;
     #10 enable = 1;
     #10 enable = 1;
     #10 enable = 1;
      #10 enable = 1;
       #10 enable = 1;
       #10 enable = 1;
       #10 enable = 1;
       #10 enable = 1;
       #10 enable = 1;
       #10 enable = 1;
       #10 enable = 1;
       #10 enable = 1;
       #10 enable = 1;
       #10 enable = 1;
       #10 enable = 1;
       #10 enable = 1;
       #10 enable = 1;

  ////// Resetear los datos y no contar
     $display("Resetear los datos y no contar");
  #10 reset = 1;
  #10 reset = 0;
  #10 enable = 0;
  #10 reset = 1;
  #10 enable = 0;
  #10 enable = 0;
  #10 enable = 0;
  #10 enable = 0;
  #10 enable = 0;
  #10 enable = 0;
  #10 enable = 0;
  #10 enable = 0;
  #10 enable = 0;
  #10 enable = 0;
  #10 enable = 0;
  #10 enable = 0;

  // Volver a iniciar contadorr
     $display("Inciar contador");
    #10 reset = 0;
  #10 enable = 1;
  #10 enable = 1;
  #10 enable = 1;
  #10 enable = 1;
  #10 enable = 1;
  #10 enable = 1;
  #10 enable = 1;
  #10 enable = 1;
  #10 enable = 1;
  #10 enable = 1;
  #10 enable = 1;
  #10 enable = 1;
  #10 enable = 1;
  #10 enable = 1;
  #10 enable = 1;
  #10 enable = 1;
  #10 enable = 1;
  #10 enable = 1;
  #10 enable = 1;
  #10 enable = 1;
  #10 enable = 1;
  #10 enable = 1;
  #10 enable = 1;
  #10 enable = 1;
  #10 enable = 1;
  #10 enable = 1;
  #10 enable = 1;
  #10 enable = 1;
  #10 enable = 1;
  #10 enable = 1;
  #10 enable = 1;
  #10 enable = 1;
  #10 enable = 1;
  #10 enable = 1;
  #10 enable = 1;
  #10 enable = 1;
  #10 enable = 1;
  #10 enable = 1;
  #10 enable = 1;
  #10 enable = 1;
  #10 enable = 1;
  #10 enable = 1;
  #10 enable = 1;
  #10 enable = 1;
  #10 enable = 1;
  #10 enable = 1;
  #10 enable = 1;
  #10 enable = 1;
  #10 enable = 1;
  #10 enable = 1;
  #10 enable = 1;
  #10 enable = 1;
  #10 enable = 1;
  #10 enable = 1;
  #10 enable = 1;
  #10 enable = 1;
  #10 enable = 1;
  #10 enable = 1;
  #10 enable = 1;
  #10 enable = 1;
  #10 enable = 1;
  #10 enable = 1;
  #10 enable = 1;
  #10 enable = 1;
  #10 enable = 1;
  #10 enable = 1;
  #10 enable = 1;
  #10 enable = 1;
  #10 enable = 1;
  #10 enable = 1;
  #10 enable = 1;
  #10 enable = 1;
  #10 enable = 1;
  #10 enable = 1;
  #10 enable = 1;




   $finish;

  end


/// GTK wave
  initial begin
   $dumpfile("lab8_tb.vcd");
   $dumpvars(0,testbench);
 end
endmodule

Contador/lab8_tb.vcd
$date
	Sat Oct 24 17:25:10 2020
$end
$version
	Icarus Verilog
$end
$timescale
	1ps
$end
$scope module testbench $end
$var wire 12 ! salidas [11:0] $end
$var reg 1 " clk $end
$var reg 12 # datos [11:0] $end
$var reg 1 $ enable $end
$var reg 1 % load $end
$var reg 1 & reset $end
$scope module c1 $end
$var wire 1 " clk $end
$var wire 12 ' datos [11:0] $end
$var wire 1 $ enable $end
$var wire 1 % load $end
$var wire 1 & rst $end
$var reg 12 ( salidas [11:0] $end
$scope begin contadorr $end
$upscope $end
$upscope $end
$upscope $end
$enddefinitions $end
#0
$dumpvars
bx (
b11011000110 '
x&
x%
x$
b11011000110 #
x"
bx !
$end
#10
1"
#15
0"
#20
1"
0&
#25
0"
#30
1"
0%
#35
0"
#40
b11011000110 !
b11011000110 (
1"
1%
#45
0"
#50
b11011000111 !
b11011000111 (
1"
1$
#55
0"
#60
b11011001000 !
b11011001000 (
1"
#65
0"
#70
b11011001001 !
b11011001001 (
1"
#75
0"
#80
b11011001010 !
b11011001010 (
1"
#85
0"
#90
b11011001011 !
b11011001011 (
1"
#95
0"
#100
b11011001100 !
b11011001100 (
1"
#105
0"
#110
b11011001101 !
b11011001101 (
1"
#115
0"
#120
b11011001110 !
b11011001110 (
1"
#125
0"
#130
b0 !
b0 (
1"
1&
#135
0"
#140
b1 !
b1 (
1"
0&
#145
0"
#150
b10 !
b10 (
1"
0%
#155
0"
#160
b11 !
b11 (
1"
#165
0"
#170
b100 !
b100 (
1"
#175
0"
#180
b101 !
b101 (
1"
#185
0"
#190
b110 !
b110 (
1"
#195
0"
#200
b111 !
b111 (
1"
#205
0"
#210
b1000 !
b1000 (
1"
#215
0"
#220
b1001 !
b1001 (
1"
#225
0"
#230
b1010 !
b1010 (
1"
#235
0"
#240
b1011 !
b1011 (
1"
#245
0"
#250
b1100 !
b1100 (
1"
#255
0"
#260
b1101 !
b1101 (
1"
#265
0"
#270
b1110 !
b1110 (
1"
#275
0"
#280
b1111 !
b1111 (
1"
#285
0"
#290
b10000 !
b10000 (
1"
#295
0"
#300
b10001 !
b10001 (
1"
#305
0"
#310
b10010 !
b10010 (
1"
#315
0"
#320
b10011 !
b10011 (
1"
#325
0"
#330
b10100 !
b10100 (
1"
#335
0"
#340
b10101 !
b10101 (
1"
#345
0"
#350
b10110 !
b10110 (
1"
#355
0"
#360
b10111 !
b10111 (
1"
#365
0"
#370
b11000 !
b11000 (
1"
#375
0"
#380
b11001 !
b11001 (
1"
#385
0"
#390
b11010 !
b11010 (
1"
#395
0"
#400
b11011 !
b11011 (
1"
#405
0"
#410
b11100 !
b11100 (
1"
#415
0"
#420
b11101 !
b11101 (
1"
#425
0"
#430
b11110 !
b11110 (
1"
#435
0"
#440
b11111 !
b11111 (
1"
#445
0"
#450
b100000 !
b100000 (
1"
#455
0"
#460
b100001 !
b100001 (
1"
#465
0"
#470
b100010 !
b100010 (
1"
#475
0"
#480
b100011 !
b100011 (
1"
#485
0"
#490
b100100 !
b100100 (
1"
#495
0"
#500
b100101 !
b100101 (
1"
#505
0"
#510
b100110 !
b100110 (
1"
#515
0"
#520
b100111 !
b100111 (
1"
#525
0"
#530
b101000 !
b101000 (
1"
#535
0"
#540
b101001 !
b101001 (
1"
#545
0"
#550
b101010 !
b101010 (
1"
#555
0"
#560
b101011 !
b101011 (
1"
#565
0"
#570
b101100 !
b101100 (
1"
#575
0"
#580
b0 !
b0 (
1"
1&
#585
0"
#590
b1 !
b1 (
1"
0&
#595
0"
#600
1"
0$
#605
0"
#610
b0 !
b0 (
1"
1&
#615
0"
#620
1"
#625
0"
#630
1"
#635
0"
#640
1"
#645
0"
#650
1"
#655
0"
#660
1"
#665
0"
#670
1"
#675
0"
#680
1"
#685
0"
#690
1"
#695
0"
#700
1"
#705
0"
#710
1"
#715
0"
#720
1"
#725
0"
#730
1"
#735
0"
#740
1"
0&
#745
0"
#750
b1 !
b1 (
1"
1$
#755
0"
#760
b10 !
b10 (
1"
#765
0"
#770
b11 !
b11 (
1"
#775
0"
#780
b100 !
b100 (
1"
#785
0"
#790
b101 !
b101 (
1"
#795
0"
#800
b110 !
b110 (
1"
#805
0"
#810
b111 !
b111 (
1"
#815
0"
#820
b1000 !
b1000 (
1"
#825
0"
#830
b1001 !
b1001 (
1"
#835
0"
#840
b1010 !
b1010 (
1"
#845
0"
#850
b1011 !
b1011 (
1"
#855
0"
#860
b1100 !
b1100 (
1"
#865
0"
#870
b1101 !
b1101 (
1"
#875
0"
#880
b1110 !
b1110 (
1"
#885
0"
#890
b1111 !
b1111 (
1"
#895
0"
#900
b10000 !
b10000 (
1"
#905
0"
#910
b10001 !
b10001 (
1"
#915
0"
#920
b10010 !
b10010 (
1"
#925
0"
#930
b10011 !
b10011 (
1"
#935
0"
#940
b10100 !
b10100 (
1"
#945
0"
#950
b10101 !
b10101 (
1"
#955
0"
#960
b10110 !
b10110 (
1"
#965
0"
#970
b10111 !
b10111 (
1"
#975
0"
#980
b11000 !
b11000 (
1"
#985
0"
#990
b11001 !
b11001 (
1"
#995
0"
#1000
b11010 !
b11010 (
1"
#1005
0"
#1010
b11011 !
b11011 (
1"
#1015
0"
#1020
b11100 !
b11100 (
1"
#1025
0"
#1030
b11101 !
b11101 (
1"
#1035
0"
#1040
b11110 !
b11110 (
1"
#1045
0"
#1050
b11111 !
b11111 (
1"
#1055
0"
#1060
b100000 !
b100000 (
1"
#1065
0"
#1070
b100001 !
b100001 (
1"
#1075
0"
#1080
b100010 !
b100010 (
1"
#1085
0"
#1090
b100011 !
b100011 (
1"
#1095
0"
#1100
b100100 !
b100100 (
1"
#1105
0"
#1110
b100101 !
b100101 (
1"
#1115
0"
#1120
b100110 !
b100110 (
1"
#1125
0"
#1130
b100111 !
b100111 (
1"
#1135
0"
#1140
b101000 !
b101000 (
1"
#1145
0"
#1150
b101001 !
b101001 (
1"
#1155
0"
#1160
b101010 !
b101010 (
1"
#1165
0"
#1170
b101011 !
b101011 (
1"
#1175
0"
#1180
b101100 !
b101100 (
1"
#1185
0"
#1190
b101101 !
b101101 (
1"
#1195
0"
#1200
b101110 !
b101110 (
1"
#1205
0"
#1210
b101111 !
b101111 (
1"
#1215
0"
#1220
b110000 !
b110000 (
1"
#1225
0"
#1230
b110001 !
b110001 (
1"
#1235
0"
#1240
b110010 !
b110010 (
1"
#1245
0"
#1250
b110011 !
b110011 (
1"
#1255
0"
#1260
b110100 !
b110100 (
1"
#1265
0"
#1270
b110101 !
b110101 (
1"
#1275
0"
#1280
b110110 !
b110110 (
1"
#1285
0"
#1290
b110111 !
b110111 (
1"
#1295
0"
#1300
b111000 !
b111000 (
1"
#1305
0"
#1310
b111001 !
b111001 (
1"
#1315
0"
#1320
b111010 !
b111010 (
1"
#1325
0"
#1330
b111011 !
b111011 (
1"
#1335
0"
#1340
b111100 !
b111100 (
1"
#1345
0"
#1350
b111101 !
b111101 (
1"
#1355
0"
#1360
b111110 !
b111110 (
1"
#1365
0"
#1370
b111111 !
b111111 (
1"
#1375
0"
#1380
b1000000 !
b1000000 (
1"
#1385
0"
#1390
b1000001 !
b1000001 (
1"
#1395
0"
#1400
b1000010 !
b1000010 (
1"
#1405
0"
#1410
b1000011 !
b1000011 (
1"
#1415
0"
#1420
b1000100 !
b1000100 (
1"
#1425
0"
#1430
b1000101 !
b1000101 (
1"
#1435
0"
#1440
b1000110 !
b1000110 (
1"
#1445
0"
#1450
b1000111 !
b1000111 (
1"
#1455
0"
#1460
b1001000 !
b1001000 (
1"
#1465
0"
#1470
b1001001 !
b1001001 (
1"
#1475
0"
#1480
b1001010 !
b1001010 (
1"
#1485
0"
#1490
b1001011 !
b1001011 (
1"
